weckup/__init__.py
weckup-0.0.1.dist-info/METADATA
weckup-0.0.1.dist-info/WHEEL
weckup-0.0.1.dist-info/RECORD
